Workbook

Sheet Instructions
C2: Instructions on How to Complete Pricing Form | G2: Estimated User Counts: to be used as a guideline for license costs
C3: Proponent must provide pricing information in the prescribed tab (green tabs) of the attached spreadsheet. | G3: High-level Functional Grouping | H3: # of Users
C4: 1) | D4: Implementation Costs | G4: Customer Service | H4: 15
C5: 2) | D5: License Costs | G5: Energy Marketers | H5: 3
C6: 3) | D6: Ongoing Operating Costs | G6: Usage, Billing, & Reporting | H6: 10
C7: 4) | D7: Hourly Resource Rates | G7: Finance | H7: 5
C8: The 5-year pricing model will be automatically populated according to the numbers provided in the above tabs for UTILITYnet's consideration (excluding Hourly Resource Rates). | G8: Executive | H8: 5
C9: Italicized texts in blue are sample descriptions for the Proponent to write over with their own descriptions /units. Additional rows within each of the tabs may be added or deleted if required, but the spreadsheet categories must be maintained as provided.
C13: Pricing Definitions:
C14: a) | D14: Rates must be provided in Canadian dollars, inclusive of all applicable duties and taxes except for applicable sales taxes, which should be itemized separately.
C15: b) | D15: Rates quoted by the proponent must be all-inclusive and must include all labour and material costs, all travel and carriage costs, all insurance costs, all costs of delivery, all costs of installation and set-up, including any pre-delivery inspection charges, and all other overhead, including any fees or other charges required by law.
C16: c) | D16: Proponent should list all assumptions relevant to the pricing information that they are providing.
C17: d) | D17: Proponent must provide pricing details on all components of their integration platform that is being proposed as part of their response to this RFP.
C18: e) | D18: Estimated user counts provided below must be used for all license pricing.
C20: Definitions:
D21: Unit: Define the unit for each item (e.g., per project, per hour, per session, per day, etc.).
D22: Cost per Unit: Specify the cost per unit.
D23: Quantity: Indicate the quantity required (e.g., number of hours, days, sessions, trips, or projects).
D24: Item Subtotal: Calculate the subtotal for the Item/Service category. Multiply the cost per unit by the quantity to get the total cost for each item.
D25: (License only) Item Yearly Subtotal: Calculate the annual subtotal for the License item (if the Unit/Duration is not calculated by annual cost).

Sheet Implementation Costs
A1: Implementation Services Cost
A2: Item/Service | B2: Description | C2: Unit | D2: Cost per Unit (excluding tax) | E2: Quantity | F2: Item Subtotal
A3: Initial Configuration & Setup | B3: Sage Intacct platform setup, AWS Canada infrastructure provisioning, Phase 0 solution design and architecture decision, vendor selection, and baseline system configuration. | C3: Per Project | D3: 540000 | E3: 1 | F3: =D3*E3 -> 540000
A4: Data Migration | B4: Oracle PL/SQL business logic extraction (AI-assisted via LegacyLift), Sage 50 historical financial data migration, data profiling, cleansing, mapping, and validation across all customer and financial records. | C4: Per Project | D4: 380000 | E4: 1 | F4: =D4*E4 -> 380000
A5: Customization & Custom Development | B5: Custom billing engine for partner marketer channel, CEM portal, self-service rate management, settlement reconciliation module, hedging dashboard, carbon credit tracking, VL Trader integration replacement, and AESO data pipeline. | C5: Per Project | D5: 980000 | E5: 1 | F5: =D5*E5 -> 980000
A6: Project Management | B6: Dedicated Project Director across all phases; weekly governance cadence, stakeholder reporting, risk management, change control, milestone tracking, and executive steering committee support. | C6: Per Project | D6: 345600 | E6: 1 | F6: =D6*E6 -> 345600
A7: Change Management & User Adoption | B7: Role-based training programs, user documentation, knowledge transfer workshops at each phase gate, and capability transfer to UTILITYnet's internal business owner and IT team. | C7: Per Project | D7: 230400 | E7: 1 | F7: =D7*E7 -> 230400
A8: Post-Implementation Support (Hypercare) | B8: 4-week intensive hypercare period immediately following each phase go-live; includes dedicated on-call support, real-time issue triage, and stabilization monitoring across Phases 1, 2, and 3. | C8: Per Project | D8: 230000 | E8: 1 | F8: =D8*E8 -> 230000
A9: Reimbursable Costs | B9: Travel and accommodation for Calgary on-site engagements (estimated 12 trips over program duration, Boston-Calgary). All travel pre-approved by UTILITYnet prior to booking. | C9: Per Trip/Expense | D9: 14500 | E9: 12 | F9: =D9*E9 -> 174000
F10: =D10*E10 -> 0
E11: Subtotal | F11: =SUM(F3:F10) -> 2880000
E12: Applicable GST | F12: =F11*0.05 -> 144000
E13: Total | F13: =SUM(F11:F12) -> 3024000
A15: Comments / Assumptions
A16: 1. All prices are in Canadian dollars (CAD), exclusive of applicable GST.
A17: 2. Phase-gated delivery: Phase 0 (Discovery) is fixed-price and the only commitment requested at signing. Phase 1–3 pricing confirmed following Phase 0 findings within ±15–20% variance.
A18: 3. Customization estimate based on full Phase 0–3 scope. Final fixed-price commitments issued per SOW at each phase gate.
A19: 4. Reimbursable costs are estimated. Only pre-approved expenses will be invoiced.
A20: 5. No offshore resources. All delivery by senior Gnar/FractalShift staff based in North America.
A21: 6. UTILITYnet provides timely access to subject-matter experts, existing system documentation, and business stakeholders. Delays in access may affect timeline.
A22: 7. Exchange rate reference: 1 USD = 1.37 CAD (February 2026). Platform license costs normalized to CAD.

Sheet Licensing Costs
A1: Software Licensing Options and Cost (Annual)
A2: Item/Service | B2: Description | C2: Unit (Duration) | D2: Cost per Unit (excluding tax) | E2: Quantity | F2: Item Subtotal | G2: Item Yearly Subtotal
A3: Sage Intacct Enterprise License | B3: Full Sage Intacct suite: GL, AP, AR, bank reconciliation, financial reporting, payroll integration, and multi-entity support. 38 named users across all functional groups. | C3: Monthly | D3: 5700 | E3: 12 | F3: =D3*E3 -> 68400 | G3: 68400
A4: AWS Canada (ca-central-1) Infrastructure | B4: Cloud hosting for all platform components in AWS Montreal region (ca-central-1). Includes compute, storage, database, networking, monitoring, and security services. All UTILITYnet data remains in Canada. | C4: Monthly | D4: 3000 | E4: 12 | F4: =D4*E4 -> 36000 | G4: 36000
A5: FractalShift Platform License (Birdseye + Watchdog OS) | B5: Annual license for Birdseye conversational analytics engine and Watchdog OS AI reliability layer. Embedded throughout the platform for conversational data access, predictive analytics, and autonomous drift correction. | C5: Monthly | D5: 4000 | E5: 12 | F5: =D5*E5 -> 48000 | G5: 48000
A6: Third-Party Integration Licenses | B6: Annual costs for VoIP platform (RingCentral/Teams Phone), email service provider (Constant Contact integration), TransUnion credit API, and AESO data feed subscriptions. | C6: Monthly | D6: 1200 | E6: 12 | F6: =D6*E6 -> 14400 | G6: 14400
A7: Document Management Integration | B7: SharePoint / Google Drive / OneDrive integration middleware for document storage, versioning, and customer record association. Annual subscription. | C7: Yearly | D7: 6000 | E7: 1 | F7: =D7*E7 -> 6000 | G7: 6000
F8: =D8*E8 -> 0
F9: Subtotal | G9: =SUM(G3:G8) -> 172800
F10: Applicable GST | G10: =G9*0.05 -> 8640
F11: Total | G11: =SUM(G9:G10) -> 181440
A14: Comments / Assumptions
A15: 1. All license pricing in CAD. USD-denominated licenses converted at 1 USD = 1.37 CAD.
A16: 2. Sage Intacct pricing based on 38 named users: 15 Customer Service, 3 Energy Marketers, 10 Billing/Ops, 5 Finance, 5 Executive.
A17: 3. AWS hosting estimate based on projected workloads; includes auto-scaling capacity. Actual costs may vary with usage.
A18: 4. FractalShift license includes Birdseye conversational analytics and Watchdog OS AI layer for the full platform.
A19: 5. Third-party licenses are estimates; final costs confirmed in Phase 0 vendor selection process.
A20: 6. Annual license costs begin at Phase 1 go-live. Pre-go-live infrastructure costs included in Implementation Costs.

Sheet Ongoing Operating Costs
A1: Ongoing Operating Costs Separate from Licensing (Annual)
A2: Item/Service | B2: Description | C2: Unit (Duration) | D2: Cost per Unit (excluding tax) | E2: Quantity | F2: Item Subtotal
A3: Managed Services Retainer (Post Go-Live) | B3: Full vendor-managed operations: Tier 1–3 help desk (business hours + 24/7 critical), platform monitoring, incident response, release management, integration maintenance, bug fixes, regulatory report execution, and proactive performance optimization. Annual contract, renewable. | C3: Monthly | D3: 41000 | E3: 12 | F3: =D3*E3 -> 492000
A4: Ongoing Training | B4: Two annual training sessions for UTILITYnet staff (refresher training, onboarding for new hires, and platform update walkthroughs). Includes session facilitation and updated training materials. | C4: Per Session | D4: 2500 | E4: 2 | F4: =D4*E4 -> 5000
C5: Monthly/Yearly | F5: =D5*E5 -> 0
E6: Subtotal | F6: =SUM(F3:F5) -> 497000
E7: Applicable GST | F7: =F6*0.05 -> 24850
E8: Total | F8: =SUM(F6:F7) -> 521850
A11: Comments / Assumptions
A12: 1. Managed Services retainer begins at Phase 1 go-live. Scope expands at each subsequent phase go-live.
A13: 2. Managed Services is an annual contract, renewed each year. New feature development is scoped separately via addendum SOW.
A14: 3. SLA tiers: P1 Critical (30-min response, 4-hr resolution), P2 High (2-hr response, 1 business day resolution), P3 Medium (4-hr response, 3 business days), P4 Low (1 business day response, next sprint).
A15: 4. Training sessions scheduled at UTILITYnet's discretion; additional sessions available at hourly resource rates.

Sheet Hourly Resource Rates
A1: Resource Rates
A2: Resource Type | B2: Resource Description | C2: Hourly Rate (excluding tax) | F2: `
A3: Project Director | B3: Responsible for overall engagement governance, executive client relationship, risk management, and delivery accountability across all phases. | C3: 225
A4: AI Strategy Lead / Solution Architect (FractalShift) | B4: AI-native architecture design, LegacyLift Oracle PL/SQL extraction, Birdseye and Watchdog OS integration, and AI roadmap delivery. | C4: 210
A5: Finance Systems Lead (Sage Intacct) | B5: Sage Intacct implementation specialist; GL/AP/AR configuration, data migration, finance integration, and reporting setup. | C5: 185
A6: Senior Integration Engineer | B6: API design and build, VL Trader integration, AESO data feeds, RBC payment systems, and third-party platform integrations. | C6: 180
A7: Senior Full-Stack Engineer | B7: Core platform development, billing engine, CEM portal, MyAccount portal, and custom module development. | C7: 165
A8: AI/ML Engineer (FractalShift) | B8: Machine learning model development, Watchdog OS configuration, predictive analytics, and agentic workflow implementation. | C8: 195
A9: QA Lead | B9: Test strategy, test automation, performance validation, regression testing, and go-live readiness sign-off. | C9: 150
A10: Front-End Engineer | B10: UI/UX implementation for MyAccount portal, CEM portal, enrollment flows, and customer-facing components. | C10: 155
A11: Business Analyst | B11: Requirements documentation, process mapping, user story development, and stakeholder workshop facilitation. | C11: 140
A12: Client Success Manager | B12: Day-to-day client communication, issue escalation, managed services coordination, and relationship health monitoring. | C12: 135
A13: Junior Software Engineer | B13: Feature development support, unit testing, bug fixing, and documentation under senior engineer supervision. | C13: 125
A18: Comments / Assumptions
A19: 1. Hourly rates are in Canadian dollars (CAD), exclusive of GST.
A20: 2. Rates apply to out-of-scope work ordered via change request or addendum SOW. In-scope work is covered under fixed-price phase commitments.
A21: 3. Minimum billing increment: 2 hours per engagement.

Sheet 5 Year Pricing Model
A1: 5 Year Pricing Model
B2: Year 0 | C2: Year 1 | D2: Year 2 | E2: Year 3 | F2: Year 4 | G2: Year 5
A3: One-time Implementation Cost | B3: ='Implementation Costs'!F11 -> 2880000 | C3: n/a | D3: n/a | E3: n/a | F3: n/a | G3: n/a
A4: Software Licensing Costs | B4: ='Licensing Costs'!$G$9 -> 172800 | C4: ='Licensing Costs'!$G$9 -> 172800 | D4: ='Licensing Costs'!$G$9 -> 172800 | E4: ='Licensing Costs'!$G$9 -> 172800 | F4: ='Licensing Costs'!$G$9 -> 172800 | G4: ='Licensing Costs'!$G$9 -> 172800
A5: On-going Operating Costs | B5: ='Ongoing Operating Costs'!$F$6 -> 497000 | C5: ='Ongoing Operating Costs'!$F$6 -> 497000 | D5: ='Ongoing Operating Costs'!$F$6 -> 497000 | E5: ='Ongoing Operating Costs'!$F$6 -> 497000 | F5: ='Ongoing Operating Costs'!$F$6 -> 497000 | G5: ='Ongoing Operating Costs'!$F$6 -> 497000
A6: Total Year Costs | B6: =SUM(B3:B5) -> 3549800 | C6: =SUM(C4:C5) -> 669800 | D6: =SUM(D4:D5) -> 669800 | E6: =SUM(E4:E5) -> 669800 | F6: =SUM(F4:F5) -> 669800 | G6: =SUM(G4:G5) -> 669800
A8: 5 Year Subtotal | G8: =SUM(B6,C6,D6,E6,F6,G6) -> 6898800
A9: Applicable GST | G9: =SUM(G8*0.05) -> 344940
A10: 5 Year Grand Total | G10: =SUM(G8,G9) -> 7243740
A12: Note: GST (5%) shown separately. All prices in Canadian dollars. Implementation pricing is phase-gated; final fixed-price commitments issued post-Discovery.
